simple_service/__init__.py
simple_service/simple_service.py
infra_simple_service-0.0.1.dist-info/METADATA
infra_simple_service-0.0.1.dist-info/WHEEL
infra_simple_service-0.0.1.dist-info/top_level.txt
infra_simple_service-0.0.1.dist-info/RECORD
