Metadata-Version: 2.1
Name: infra-simple-service
Version: 0.0.1
Summary: Template and testing purposes
License: The MIT License (MIT)
Requires-Dist: requests
